.coveragerc
.gitignore
.readthedocs.yml
.style.yapf
.travis.yml
CHANGELOG.rst
LICENSE
Makefile
README.rst
mktag
pylintrc
setup.cfg
setup.py
tox.ini
ci/rtd-requirements.txt
ci/test-requirements.txt
ci/travis.sh
debian/.gitignore
debian/changelog
debian/compat
debian/control
debian/rules
debian/watch
debian/source/format
docs/Makefile
docs/make.bat
docs/source/conf.py
docs/source/history.rst
docs/source/index.rst
docs/source/rationale.rst
docs/source/usage.rst
docs/source/_static/.git_empty
examples/hammer.py
examples/listener.py
tests/__init__.py
tests/test_client.py
tests/test_client_stream.py
tests/test_connection.py
tests/test_environmentconfig.py
tests/test_result.py
trio_serf/__init__.py
trio_serf/_version.py
trio_serf/client.py
trio_serf/codec.py
trio_serf/connection.py
trio_serf/environment_config.py
trio_serf/exceptions.py
trio_serf/result.py
trio_serf/stream.py
trio_serf/util.py
trio_serf.egg-info/PKG-INFO
trio_serf.egg-info/SOURCES.txt
trio_serf.egg-info/dependency_links.txt
trio_serf.egg-info/requires.txt
trio_serf.egg-info/top_level.txt