Metadata-Version: 1.2
Name: trio-serf
Version: 0.4.0
Summary: Python client for the Serf orchestration tool
Home-page: https://github.com/smurfix/trio-serf
Author: Matthias Urlichs
Author-email: matthias@urlichs.de
Maintainer: Matthias Urlichs
Maintainer-email: matthias@urlichs.de
License: MIT
Keywords: Serf,orchestration,service discovery,trio
Platform: UNKNOWN
Requires-Python: >=3.6
